{
  "photos": [
    {
      "category": "nature",
      "images": [
        { "src": "/nature/airplane.jpeg" },
        { "src": "/nature/alidanino.jpeg" },
        { "src": "/nature/cat.jpg" },
        { "src": "/nature/delphini.jpg" },
        { "src": "/nature/sabachka.jpg" },
        { "src": "/nature/fish2.jpeg" },
        { "src": "/nature/fish.jpeg" },
        { "src": "/nature/frani.jpg" },
        { "src": "/nature/gemi.jpeg" },
        { "src": "/nature/meezove.jpeg" },
        { "src": "/nature/xidi.jpeg" }
      ]
    },
    {
      "category": "people",
      "images": [
        { "src": "/people/anna.jpeg" },
        { "src": "/people/babu.jpg" },
        { "src": "/people/babu2.jpg" },
        { "src": "/people/bichi.jpeg" },
        { "src": "/people/ckvili.jpg" },
        { "src": "/people/couple.jpeg" },
        { "src": "/people/dea.jpeg" },
        { "src": "/people/image0011.png" },
        { "src": "/people/lenka.jpeg" },
        { "src": "/people/mamao.jpg" },
        { "src": "/people/nini.jpeg" },
        { "src": "/people/velosipedi.jpg" }
      ]
    },
    {
      "category": "food",
      "images": [
        { "src": "/food/blueyellow.jpeg" },
        { "src": "/food/cezari.jpeg" },
        { "src": "/food/cheescake.jpeg" },
        { "src": "/food/coctail.jpeg" },
        { "src": "/food/Food.png" },
        { "src": "/food/keku.jpeg" },
        { "src": "/food/kitri.jpeg" },
        { "src": "/food/kvercxi.jpeg" },
        { "src": "/food/orange.png" },
        { "src": "/food/red.jpeg" },
        { "src": "/food/salati.jpeg" },
        { "src": "/food/shampanuri.jpeg" },
        { "src": "/food/sufra.jpeg" },
        { "src": "/food/tiramisu.jpeg" },
        { "src": "/food/xachapuri.jpeg" },
        { "src": "/food/xorci.jpeg" }
      ]
    },
    {
      "category": "interior",
      "images": [
        { "src": "/interior/interior1.jpeg" },
        { "src": "/interior/interior2.jpg" },
        { "src": "/interior/interior3.jpeg" },
        { "src": "/interior/interior4.jpeg" },
        { "src": "/interior/interior5.jpg" },
        { "src": "/interior/interior5.png" }
      ]
    }
  ]
}
